LICENSE
MANIFEST.in
README.md
requirements.txt
setup.py
connexion_compose/__init__.py
connexion_compose/compiler.py
connexion_compose/validators.py
connexion_compose.egg-info/PKG-INFO
connexion_compose.egg-info/SOURCES.txt
connexion_compose.egg-info/dependency_links.txt
connexion_compose.egg-info/requires.txt
connexion_compose.egg-info/top_level.txt
connexion_compose/schemas/root.yml
connexion_compose/schemas/definitions/types.yml
requirements/base.txt
requirements/dev.txt
requirements/test.txt