Metadata-Version: 2.1
Name: connexion-compose
Version: 0.3.2
Summary: Create Connexion schema composed from several files in a nested directory structure.
Home-page: https://gitlab.com/jsmesami/connexion-compose
Author: Ondřej Nejedlý
Author-email: jsmesami@gmail.com
License: MIT
Keywords: connexion swagger schema compose
Platform: UNKNOWN
Classifier: Development Status :: 5 - Production/Stable
Classifier: Operating System :: OS Independent
Classifier: Intended Audience :: Developers
Classifier: Topic :: Software Development :: Libraries :: Python Modules
Classifier: License :: OSI Approved :: MIT License
Classifier: Programming Language :: Python :: 3.7
Classifier: Programming Language :: Python :: 3.8
Classifier: Programming Language :: Python :: 3.9
Requires-Python: >=3.7
License-File: LICENSE
